ittia/__init__.py
ittia/api/check.py
ittia-0.1.0.dist-info/METADATA
ittia-0.1.0.dist-info/WHEEL
ittia-0.1.0.dist-info/RECORD
